vecno_script_address/__init__.py
vecno_script_address/vecno_script_address.abi3.so
vecno_script_address-0.0.1.dist-info/METADATA
vecno_script_address-0.0.1.dist-info/WHEEL
vecno_script_address-0.0.1.dist-info/licenses/LICENSE
vecno_script_address-0.0.1.dist-info/RECORD
