Metadata-Version: 2.4
Name: vecno_script_address
Version: 0.0.1
License-File: LICENSE
License-File: LICENSE
Summary: Python bindings for Vecno script address utilities and parsing
Keywords: vecno,blockchain,script,address
Home-Page: https://vecnofoundation.org
Author-email: Yoshiki <yoshiki@vecnofoundation.org>
